muxkt/config.py
muxkt/main.py
muxkt/mux.py
muxkt/selection.py
muxkt/utils.py
muxkt-0.3.0.dist-info/LICENSE
muxkt-0.3.0.dist-info/METADATA
muxkt-0.3.0.dist-info/WHEEL
muxkt-0.3.0.dist-info/entry_points.txt
muxkt-0.3.0.dist-info/RECORD
