Metadata-Version: 2.1
Name: muxkt
Version: 0.3.0
Summary: Wrapper for SubKt written in python
Home-page: https://github.com/PhosCity/muxkt
License: GPL-3.0-or-later
Author: PhosCity
Author-email: phoscity2@gmail.com
Requires-Python: >=3.12,<4.0
Classifier: License :: OSI Approved :: GNU General Public License v3 or later (GPLv3+)
Classifier: Programming Language :: Python :: 3
Classifier: Programming Language :: Python :: 3.12
Requires-Dist: click (>=8.1.7,<9.0.0)
Requires-Dist: iterfzf (>=1.4.0.54.3,<2.0.0.0.0)
Requires-Dist: rich (>=13.9.4,<14.0.0)
